autorch_sphinx_theme/__init__.py
autorch_sphinx_theme/breadcrumbs.html
autorch_sphinx_theme/cookie_banner.html
autorch_sphinx_theme/fonts.html
autorch_sphinx_theme/footer.html
autorch_sphinx_theme/layout.html
autorch_sphinx_theme/search.html
autorch_sphinx_theme/searchbox.html
autorch_sphinx_theme/theme.conf
autorch_sphinx_theme/theme_variables.jinja
autorch_sphinx_theme/versions.html
autorch_sphinx_theme/static/css/theme.css
autorch_sphinx_theme/static/images/arrow-down-orange.svg
autorch_sphinx_theme/static/images/arrow-right-with-tail.svg
autorch_sphinx_theme/static/images/chevron-down-grey.svg
autorch_sphinx_theme/static/images/chevron-down-orange.svg
autorch_sphinx_theme/static/images/chevron-right-orange.svg
autorch_sphinx_theme/static/images/chevron-right-white.svg
autorch_sphinx_theme/static/images/home-footer-background.jpg
autorch_sphinx_theme/static/images/icon-close.svg
autorch_sphinx_theme/static/images/icon-menu-dots-dark.svg
autorch_sphinx_theme/static/images/logo-dark.svg
autorch_sphinx_theme/static/images/logo-facebook-dark.svg
autorch_sphinx_theme/static/images/logo-icon.svg
autorch_sphinx_theme/static/images/logo-twitter-dark.svg
autorch_sphinx_theme/static/images/logo-youtube-dark.svg
autorch_sphinx_theme/static/images/logo.svg
autorch_sphinx_theme/static/images/pytorch-colab.svg
autorch_sphinx_theme/static/images/pytorch-download.svg
autorch_sphinx_theme/static/images/pytorch-github.svg
autorch_sphinx_theme/static/images/pytorch-x.svg
autorch_sphinx_theme/static/images/search-icon.svg
autorch_sphinx_theme/static/images/view-page-source-icon.svg
autorch_sphinx_theme/static/js/modernizr.min.js
autorch_sphinx_theme/static/js/theme.js
autorch_sphinx_theme-0.0.24b20201029.dist-info/LICENSE
autorch_sphinx_theme-0.0.24b20201029.dist-info/METADATA
autorch_sphinx_theme-0.0.24b20201029.dist-info/WHEEL
autorch_sphinx_theme-0.0.24b20201029.dist-info/entry_points.txt
autorch_sphinx_theme-0.0.24b20201029.dist-info/top_level.txt
autorch_sphinx_theme-0.0.24b20201029.dist-info/RECORD
