Metadata-Version: 2.1
Name: autorch-sphinx-theme
Version: 0.0.24b20201029
Summary: PyTorch Sphinx Theme
Home-page: https://github.com/StacyYang/autorch_sphinx_theme
Author: Shift Lab
Author-email: info@shiftlabny.com
License: MIT License
Platform: UNKNOWN
Classifier: Development Status :: 5 - Production/Stable
Classifier: Environment :: Web Environment
Classifier: Intended Audience :: Developers
Classifier: Intended Audience :: System Administrators
Classifier: License :: OSI Approved :: MIT License
Classifier: Operating System :: OS Independent
Classifier: Programming Language :: Python
Classifier: Topic :: Internet
Classifier: Topic :: Software Development :: Documentation
Requires-Dist: sphinx
